gsrace/__init__.py
gsrace/__main__.py
gsrace/_bar_chart_race.py
gsrace/_bar_chart_race_plotly.py
gsrace/_colormaps.py
gsrace/_common_chart.py
gsrace/_func_animation.py
gsrace/_line_chart_race.py
gsrace/_navigator.py
gsrace/_pandas_accessor.py
gsrace/_proxy_generator.py
gsrace/_scholarly.py
gsrace/_utils.py
gsrace/author_parser.py
gsrace/data_types.py
gsrace/publication_parser.py
gsrace/utils.py
gsrace/version.py
gsrace-0.0.2.dist-info/LICENSE.md
gsrace-0.0.2.dist-info/METADATA
gsrace-0.0.2.dist-info/WHEEL
gsrace-0.0.2.dist-info/entry_points.txt
gsrace-0.0.2.dist-info/top_level.txt
gsrace-0.0.2.dist-info/RECORD
