Metadata-Version: 2.1
Name: gsrace
Version: 0.0.2
Summary: A tool to show the journals trends for a user's Google Scholar publications.
Home-page: https://github.com/faridrashidi/gscholar-race
Author: Farid Rashidi
Author-email: farid.rsh@gmail.com
License: MIT
Project-URL: Source, https://github.com/faridrashidi/gscholar-race
Keywords: google scholar race cli
Platform: UNKNOWN
Requires-Python: >=3.6
License-File: LICENSE.md
Requires-Dist: tqdm
Requires-Dist: pandas
Requires-Dist: matplotlib
Requires-Dist: click
Requires-Dist: joblib
Requires-Dist: arrow
Requires-Dist: beautifulsoup4
Requires-Dist: bibtexparser
Requires-Dist: deprecated
Requires-Dist: fake-useragent
Requires-Dist: free-proxy
Requires-Dist: python-dotenv
Requires-Dist: requests[socks]
Requires-Dist: selenium
Requires-Dist: stem
